[
  {
    "id": "1",
    "command1": {
      "name": "Биолог",
      "logo": "BIOLOG",
      "redCardNumber": "6",
      "goals": 4
    },
    "command2": {
      "name": "Велес Москва",
      "logo": "VELES_MOSCOW",
      "redCardNumber": "5",
      "goals": 1
    },
    "time": "Закончен"
  },
  {
    "id": "2",
    "command1": {
      "name": "УФА (Ж)",
      "logo": "UFA_G",
      "redCardNumber": "6",
      "goals": 4
    },
    "command2": {
      "name": "Коломна",
      "logo": "KOLOMNA",
      "redCardNumber": "3",
      "goals": 2
    },
    "time": "2-й тайм"
  },
  {
    "id": "3",
    "command1": {
      "name": "Локомотив",
      "logo": "LOCOMOTIV",
      "goals": 0
    },
    "command2": {
      "name": "Динамо Брянск",
      "logo": "DINAMO_BRYANSK",
      "goals": 0
    },
    "time": "Не начался"
  }
]
